selenium_google_signin/__init__.py
selenium_google_signin/_config.py
selenium_google_signin/_google_login.py
selenium_google_signin/_util.py
selenium_google_signin-0.1.5.dist-info/LICENSE
selenium_google_signin-0.1.5.dist-info/METADATA
selenium_google_signin-0.1.5.dist-info/WHEEL
selenium_google_signin-0.1.5.dist-info/top_level.txt
selenium_google_signin-0.1.5.dist-info/RECORD
