Metadata-Version: 2.1
Name: selenium_google_signin
Version: 0.1.5
Summary: Helps you sign in to Google and remember it automatically.
Author-email: ksks <nose2002kr@gmail.com>
Project-URL: Repository, https://github.com/nose2002kr/selenium-google-signin.git
Project-URL: Issues, https://github.com/nose2002kr/selenium-google-signin/issues
Keywords: selenium,login,signin,cookies
Classifier: Programming Language :: Python :: 3
Classifier: License :: OSI Approved :: MIT License
Classifier: Operating System :: OS Independent
Requires-Python: >=3.8
License-File: LICENSE
Requires-Dist: selenium ==4.23.0
Requires-Dist: platformdirs ==4.2.2
Provides-Extra: config
Requires-Dist: python-dotenv ; extra == 'config'
Provides-Extra: logger
Requires-Dist: loguru ; extra == 'logger'
Provides-Extra: webdriver
Requires-Dist: webdriver-manager ; extra == 'webdriver'
